wagtail_block_fields/__init__.py
wagtail_block_fields/fields.py
wagtail_block_fields-0.2.0.dist-info/METADATA
wagtail_block_fields-0.2.0.dist-info/WHEEL
wagtail_block_fields-0.2.0.dist-info/licenses/LICENSE
wagtail_block_fields-0.2.0.dist-info/RECORD
