Metadata-Version: 2.4
Name: wagtail-block-fields
Version: 0.2.0
Summary: Allows using StructBlock and ListBlock as model fields
Project-URL: Repository, https://github.com/joeyjurjens/wagtail-block-fields
Author-email: Joey Jurjens <joeyjurjens@gmail.com>
License-Expression: MIT
License-File: LICENSE
Requires-Python: >=3.10
Requires-Dist: wagtail>=6.3
